2af26aff91d674569c1b__mypyc.cpython-311-aarch64-linux-gnu.so
pybf/compiler.cpython-311-aarch64-linux-gnu.so
pybf/__main__.py
pybf/constants.py
pybf/__init__.py
pybf/interpreter.py
pybf/compiler.py
pybf/interpreter.cpython-311-aarch64-linux-gnu.so
ng.pybf-1.0.2.dist-info/LICENSE
ng.pybf-1.0.2.dist-info/entry_points.txt
ng.pybf-1.0.2.dist-info/WHEEL
ng.pybf-1.0.2.dist-info/top_level.txt
ng.pybf-1.0.2.dist-info/RECORD
ng.pybf-1.0.2.dist-info/METADATA
