Metadata-Version: 2.1
Name: ng.pybf
Version: 1.0.2
Summary: py.bf: Python interpreter and C transpiler/compiler for brainfuck
Author-email: Yuanhao 'Nyoeghau' Chen <nyoeghau@nyoeghau.com>
License: # MIT License
Project-URL: Homepage, https://github.com/edward-martyr/test.pypi
Project-URL: Bug Tracker, https://github.com/edward-martyr/test.pypi/issues
Classifier: Programming Language :: Python :: 3.10
Classifier: Programming Language :: Python :: 3.11
Classifier: License :: OSI Approved :: MIT License
Classifier: Development Status :: 1 - Planning
Classifier: Operating System :: OS Independent
Classifier: Topic :: Software Development :: Interpreters
Requires-Python: >=3.10
License-File: LICENSE
Requires-Dist: setuptools (>=62)
Provides-Extra: lint
Requires-Dist: black (<23,>=22.6.0) ; extra == 'lint'
Requires-Dist: flake8 (<5,>=4.0.1) ; extra == 'lint'
Requires-Dist: isort (<6,>=5.10.1) ; extra == 'lint'
Requires-Dist: mypy (<1,>=0.971) ; extra == 'lint'
